traph/__init__.py
traph/helpers.py
traph/traph.py
traph/traph_iterator_state.py
traph/traph_write_report.py
traph/version.py
traph/link_store/__init__.py
traph/link_store/header.py
traph/link_store/link_store.py
traph/link_store/node.py
traph/lru_trie/__init__.py
traph/lru_trie/header.py
traph/lru_trie/lru_trie.py
traph/lru_trie/node.py
traph/lru_trie/walk_history.py
traph/storage/__init__.py
traph/storage/file.py
traph/storage/memmap.py
traph/storage/memory.py
hyphe_traph-3.0.0.dist-info/LICENSE.txt
hyphe_traph-3.0.0.dist-info/METADATA
hyphe_traph-3.0.0.dist-info/WHEEL
hyphe_traph-3.0.0.dist-info/top_level.txt
hyphe_traph-3.0.0.dist-info/zip-safe
hyphe_traph-3.0.0.dist-info/RECORD
