Metadata-Version: 2.1
Name: hyphe-traph
Version: 3.0.0
Summary: A Trie/Graph hybrid memory structure used by the Hyphe crawler to index pages & webentities.
Home-page: http://github.com/medialab/hyphe-traph
Author: Guillaume Plique, Béatrice Mazoyer
License: MIT
License-File: LICENSE.txt
